kvakk_git_tools/__init__.py
kvakk_git_tools/recommended/gitattributes
kvakk_git_tools/recommended/gitconfig-adm-mac
kvakk_git_tools/recommended/gitconfig-dapla
kvakk_git_tools/recommended/gitconfig-dapla-lab
kvakk_git_tools/recommended/gitconfig-prod-linux
kvakk_git_tools/recommended/gitconfig-prod-windows-citrix
kvakk_git_tools/recommended/gitignore
kvakk_git_tools/ssb_gitconfig.py
kvakk_git_tools/validate_ssb_gitconfig.py
kvakk_git_tools/validate_ssb_local_git_files.py
kvakk_git_tools-2.5.1.dist-info/LICENSE
kvakk_git_tools-2.5.1.dist-info/METADATA
kvakk_git_tools-2.5.1.dist-info/WHEEL
kvakk_git_tools-2.5.1.dist-info/entry_points.txt
kvakk_git_tools-2.5.1.dist-info/RECORD
