Metadata-Version: 2.3
Name: kvakk-git-tools
Version: 2.5.1
Summary: Recommended git config and git scripts for Statistics Norway.
License: MIT
Author: Arne Sørli
Author-email: 81353974+arneso-ssb@users.noreply.github.com
Requires-Python: >=3.10,<4.0
Classifier: License :: OSI Approved :: MIT License
Classifier: Programming Language :: Python :: 3
Classifier: Programming Language :: Python :: 3.10
Classifier: Programming Language :: Python :: 3.11
Classifier: Programming Language :: Python :: 3.12
Classifier: Programming Language :: Python :: 3.13
